glfy/__init__.py
glfy/ascii_conversion.py
glfy/cli.py
glfy/config.py
glfy/core.py
glfy/glfy_imports.py
glfy/helpers.py
glfy/image_processing.py
glfy/live_video_processing.py
glfy/utils.py
glfy/video_processing.py
glfy/fonts/courier-new/cour.ttf
glfy/fonts/courier-new/courbd.ttf
glfy/fonts/dejavu-sans/DejaVuSans-Bold.ttf
glfy/fonts/dejavu-sans/DejaVuSans.ttf
glfy-1.0.3.dist-info/METADATA
glfy-1.0.3.dist-info/WHEEL
glfy-1.0.3.dist-info/entry_points.txt
glfy-1.0.3.dist-info/top_level.txt
glfy-1.0.3.dist-info/RECORD
